{
"type": "FeatureCollection",
"name": "BooneOakley_point_4326_json",
"crs": { "type": "name", "properties": { "name": "urn:ogc:def:crs:OGC:1.3:CRS84" } },
"features": [
{ "type": "Feature", "properties": { "id": 1, "Location": "BooneOakley" }, "geometry": { "type": "Point", "coordinates": [ -80.860137777970223, 35.219169693089597 ] } }
]
}
